scripts/__init__.py
scripts/imseq2ting.py
ting/__init__.py
ting/ting.py
bio_ting-1.1.0.dist-info/LICENSE
bio_ting-1.1.0.dist-info/METADATA
bio_ting-1.1.0.dist-info/WHEEL
bio_ting-1.1.0.dist-info/entry_points.txt
bio_ting-1.1.0.dist-info/top_level.txt
bio_ting-1.1.0.dist-info/RECORD
