Metadata-Version: 2.1
Name: bio-ting
Version: 1.1.0
Summary: ting - T cell receptor interaction grouping
Home-page: https://github.com/FelixMoelder/ting
Author: Felix Mölder
Author-email: felix.moelder@uni-due.de
License: MIT License
Platform: UNKNOWN
Classifier: Development Status :: 5 - Production/Stable
Classifier: Environment :: Console
Classifier: Intended Audience :: Science/Research
Classifier: License :: OSI Approved :: MIT License
Classifier: Programming Language :: Python :: 3
Classifier: Topic :: Scientific/Engineering :: Bio-Informatics
Requires-Dist: numpy (<=1.19,>=1.17)
Requires-Dist: scipy (<=1.5,>=1.3)
